{
  "items": [
    {
      "title": "인기있는 질문글 1",
      "context": "인기있는 질문내용 1",
      "reply": "인기있는 질문답변 1",
      "recom": "1000"
    },
    {
      "title": "인기있는 질문글 2",
      "context": "인기있는 질문내용 2",
      "reply": "인기있는 질문답변 2",
      "recom": "1000"
    },
    {
      "title": "인기있는 질문글 3",
      "context": "인기있는 질문내용 3",
      "reply": "인기있는 질문답변 3",
      "recom": "1000"
    },
    {
      "title": "인기있는 질문글 4",
      "context": "인기있는 질문내용 4",
      "reply": "인기있는 질문답변 4",
      "recom": "1000"
    },
    {
      "title": "인기있는 질문글 5",
      "context": "인기있는 질문내용 5",
      "reply": "인기있는 질문답변 5",
      "recom": "1000"
    },
    {
      "title": "인기있는 질문글 6",
      "context": "인기있는 질문내용 6",
      "reply": "인기있는 질문답변 6",
      "recom": "1000"
    },
    {
      "title": "인기있는 질문글 7",
      "context": "인기있는 질문내용 7",
      "reply": "인기있는 질문답변 7",
      "recom": "1000"
    },
    {
      "title": "인기있는 질문글 8",
      "context": "인기있는 질문내용 8",
      "reply": "인기있는 질문답변 8",
      "recom": "1000"
    }
  ]
}